psiz/__init__.py
psiz/version.py
psiz/data/__init__.py
psiz/data/dataset.py
psiz/data/dataset_component.py
psiz/data/sample_qr_sets.py
psiz/data/unravel_timestep.py
psiz/data/contents/__init__.py
psiz/data/contents/categorize.py
psiz/data/contents/content.py
psiz/data/contents/rank.py
psiz/data/contents/rate.py
psiz/data/generators/__init__.py
psiz/data/generators/content_generator.py
psiz/data/generators/rank_generator.py
psiz/data/generators/experimental/weighted_rank.py
psiz/data/groups/__init__.py
psiz/data/groups/group.py
psiz/data/outcomes/__init__.py
psiz/data/outcomes/continuous.py
psiz/data/outcomes/outcome.py
psiz/data/outcomes/sparse_categorical.py
psiz/keras/__init__.py
psiz/keras/constraints/__init__.py
psiz/keras/constraints/center.py
psiz/keras/constraints/greater_equal_than.py
psiz/keras/constraints/greater_than.py
psiz/keras/constraints/less_equal_than.py
psiz/keras/constraints/less_than.py
psiz/keras/constraints/min_max.py
psiz/keras/constraints/non_neg_norm.py
psiz/keras/initializers/__init__.py
psiz/keras/initializers/dirichlet.py
psiz/keras/initializers/softplus_uniform.py
psiz/keras/layers/__init__.py
psiz/keras/layers/combiner.py
psiz/keras/layers/drop.py
psiz/keras/layers/splitter.py
psiz/keras/layers/variational.py
psiz/keras/layers/activations/__init__.py
psiz/keras/layers/activations/exponential.py
psiz/keras/layers/activations/heavy_tailed.py
psiz/keras/layers/activations/inverse.py
psiz/keras/layers/activations/students_t.py
psiz/keras/layers/behaviors/__init__.py
psiz/keras/layers/behaviors/logistic.py
psiz/keras/layers/behaviors/soft_rank.py
psiz/keras/layers/behaviors/soft_rank_base.py
psiz/keras/layers/behaviors/experimental/__init__.py
psiz/keras/layers/behaviors/experimental/alcove_cell.py
psiz/keras/layers/behaviors/experimental/soft_rank_cell.py
psiz/keras/layers/embeddings/__init__.py
psiz/keras/layers/embeddings/embedding_shared.py
psiz/keras/layers/embeddings/embedding_variational.py
psiz/keras/layers/embeddings/gamma_diag.py
psiz-0.12.2.dist-info/LICENSE
psiz-0.12.2.dist-info/METADATA
psiz-0.12.2.dist-info/WHEEL
psiz-0.12.2.dist-info/top_level.txt
psiz-0.12.2.dist-info/RECORD
