Metadata-Version: 2.1
Name: psiz
Version: 0.12.2
Summary: Toolbox for inferring psychological embeddings.
Home-page: https://github.com/psiz-org/psiz
Author: Brett D. Roads
Author-email: brett.roads@gmail.com
License: Apache Licence 2.0
Project-URL: Documentation, https://psiz.readthedocs.io/en/latest/
Project-URL: Source, https://github.com/psiz-org/psiz
Project-URL: Tracker, https://github.com/psiz-org/psiz/issues
Keywords: psychology,cognitive science
Classifier: Development Status :: 3 - Alpha
Classifier: Topic :: Scientific/Engineering
Classifier: Topic :: Scientific/Engineering :: Mathematics
Classifier: Topic :: Software Development
Classifier: Topic :: Software Development :: Libraries
Classifier: Topic :: Software Development :: Libraries :: Python Modules
Classifier: License :: OSI Approved :: Apache Software License
Classifier: Programming Language :: Python :: 3
Classifier: Programming Language :: Python :: 3.9
Classifier: Programming Language :: Python :: 3.10
Classifier: Programming Language :: Python :: 3.11
Classifier: Programming Language :: Python :: 3 :: Only
Requires-Python: <3.12,>=3.9
License-File: LICENSE
Requires-Dist: keras<4.0,>=3.5
Requires-Dist: tensorflow<2.17.0,>=2.16.2
Requires-Dist: tensorflow-probability
Requires-Dist: tf-keras
Requires-Dist: torch>=2.4
Requires-Dist: h5py>=3.0
Requires-Dist: pandas
Requires-Dist: scikit-learn
Requires-Dist: matplotlib
Requires-Dist: pillow
Requires-Dist: imageio
Provides-Extra: doc
Requires-Dist: sphinx-rtd-theme==1.0.0; extra == "doc"
Requires-Dist: sphinx-last-updated-by-git; extra == "doc"
Requires-Dist: myst-nb; extra == "doc"
Requires-Dist: sphinxcontrib-bibtex; extra == "doc"
Provides-Extra: test
Requires-Dist: pytest>=6.2.4; extra == "test"
Requires-Dist: pytest-cov; extra == "test"
Requires-Dist: flake8; extra == "test"
Requires-Dist: pylint; extra == "test"
